pylivoltek/__init__.py
pylivoltek/api_client.py
pylivoltek/configuration.py
pylivoltek/rest.py
pylivoltek/api/__init__.py
pylivoltek/api/default_api.py
pylivoltek/models/__init__.py
pylivoltek/models/api_login_body.py
pylivoltek/models/api_response.py
pylivoltek/models/current_power_flow.py
pylivoltek/models/device.py
pylivoltek/models/device_details.py
pylivoltek/models/device_list.py
pylivoltek/models/energy_store.py
pylivoltek/models/energy_store_battery_type.py
pylivoltek/models/energy_store_history_map.py
pylivoltek/models/energy_store_history_map_item.py
pylivoltek/models/grid_import_export.py
pylivoltek/models/grid_import_export_api_response.py
pylivoltek/models/grid_import_export_list.py
pylivoltek/models/inline_response200.py
pylivoltek/models/inline_response2001.py
pylivoltek/models/inline_response2001_data.py
pylivoltek/models/inline_response2002.py
pylivoltek/models/inline_response2003.py
pylivoltek/models/inline_response2004.py
pylivoltek/models/inline_response2005.py
pylivoltek/models/inline_response2006.py
pylivoltek/models/inline_response2007.py
pylivoltek/models/site.py
pylivoltek/models/site_list.py
pylivoltek/models/site_overview.py
pylivoltek/models/solar_generation.py
pylivoltek/models/solar_generation_api_response.py
pylivoltek/models/solar_generationt_list.py
test/__init__.py
test/test_api_login_body.py
test/test_api_response.py
test/test_current_power_flow.py
test/test_default_api.py
test/test_device.py
test/test_device_details.py
test/test_device_list.py
test/test_energy_storage_controller.py
test/test_energy_store.py
test/test_energy_store_battery_type.py
test/test_energy_store_history_map.py
test/test_energy_store_history_map_item.py
test/test_grid_import_export.py
test/test_grid_import_export_api_response.py
test/test_grid_import_export_history.py
test/test_grid_import_export_list.py
test/test_history_item.py
test/test_inline_response200.py
test/test_inline_response2001.py
test/test_inline_response2001_data.py
pylivoltek-1.0.9.dist-info/METADATA
pylivoltek-1.0.9.dist-info/WHEEL
pylivoltek-1.0.9.dist-info/top_level.txt
pylivoltek-1.0.9.dist-info/RECORD
